drf/__init__.py
drf/code.py
sempler/__init__.py
sempler/anm.py
sempler/functions.py
sempler/generators.py
sempler/lganm.py
sempler/noise.py
sempler/normal_distribution.py
sempler/plot.py
sempler/semi.py
sempler/utils.py
sempler-0.2.14.dist-info/LICENSE.txt
sempler-0.2.14.dist-info/METADATA
sempler-0.2.14.dist-info/WHEEL
sempler-0.2.14.dist-info/top_level.txt
sempler-0.2.14.dist-info/RECORD
