Metadata-Version: 2.1
Name: sempler
Version: 0.2.14
Summary: Sample from general structural causal models (SCMs).
Home-page: https://github.com/juangamella/sempler
Author: Juan L Gamella
Author-email: juangamella@gmail.com
License: BSD 3-Clause License
License-File: LICENSE.txt
Requires-Dist: numpy >=1.17.0
Requires-Dist: pandas >=1.2.1
Provides-Extra: drfnet
Requires-Dist: rpy2 >=3.4.1 ; extra == 'drfnet'
